flashsale_planner/__init__.py
flashsale_planner/flashsale_planner.py
flashsale_planner-0.0.6.dist-info/LICENSE.txt
flashsale_planner-0.0.6.dist-info/METADATA
flashsale_planner-0.0.6.dist-info/WHEEL
flashsale_planner-0.0.6.dist-info/top_level.txt
flashsale_planner-0.0.6.dist-info/RECORD
