Metadata-Version: 2.1
Name: flashsale-planner
Version: 0.0.6
Summary: A package serving as a planning tool for sellers on Shopee flash sale
Home-page: https://github.com/papillonbee/flashsale_planner
Author: Papan Yongmalwong
Author-email: papillonbee@gmail.com
License: UNKNOWN
Platform: UNKNOWN
Classifier: Programming Language :: Python :: 3
Classifier: License :: OSI Approved :: MIT License
Classifier: Operating System :: OS Independent
Requires-Python: >=3.6
